autogen/__init__.py
autogen/_pydantic.py
autogen/browser_utils.py
autogen/code_utils.py
autogen/exception_utils.py
autogen/formatting_utils.py
autogen/function_utils.py
autogen/graph_utils.py
autogen/math_utils.py
autogen/retrieve_utils.py
autogen/runtime_logging.py
autogen/token_count_utils.py
autogen/types.py
autogen/version.py
autogen/agentchat/__init__.py
autogen/agentchat/agent.py
autogen/agentchat/assistant_agent.py
autogen/agentchat/chat.py
autogen/agentchat/conversable_agent.py
autogen/agentchat/groupchat.py
autogen/agentchat/user_proxy_agent.py
autogen/agentchat/utils.py
autogen/agentchat/contrib/__init__.py
autogen/agentchat/contrib/agent_builder.py
autogen/agentchat/contrib/agent_optimizer.py
autogen/agentchat/contrib/gpt_assistant_agent.py
autogen/agentchat/contrib/img_utils.py
autogen/agentchat/contrib/llamaindex_conversable_agent.py
autogen/agentchat/contrib/llava_agent.py
autogen/agentchat/contrib/math_user_proxy_agent.py
autogen/agentchat/contrib/multimodal_conversable_agent.py
autogen/agentchat/contrib/qdrant_retrieve_user_proxy_agent.py
autogen/agentchat/contrib/retrieve_assistant_agent.py
autogen/agentchat/contrib/retrieve_user_proxy_agent.py
autogen/agentchat/contrib/society_of_mind_agent.py
autogen/agentchat/contrib/text_analyzer_agent.py
autogen/agentchat/contrib/web_surfer.py
autogen/agentchat/contrib/capabilities/__init__.py
autogen/agentchat/contrib/capabilities/agent_capability.py
autogen/agentchat/contrib/capabilities/generate_images.py
autogen/agentchat/contrib/capabilities/teachability.py
autogen/agentchat/contrib/capabilities/text_compressors.py
autogen/agentchat/contrib/capabilities/transform_messages.py
autogen/agentchat/contrib/capabilities/transforms.py
autogen/agentchat/contrib/capabilities/transforms_util.py
autogen/agentchat/contrib/capabilities/vision_capability.py
autogen/agentchat/contrib/vectordb/__init__.py
autogen/agentchat/contrib/vectordb/base.py
autogen/agentchat/contrib/vectordb/chromadb.py
mypyautogen20240904-0.2.35.dist-info/LICENSE
mypyautogen20240904-0.2.35.dist-info/LICENSE-CODE
mypyautogen20240904-0.2.35.dist-info/METADATA
mypyautogen20240904-0.2.35.dist-info/WHEEL
mypyautogen20240904-0.2.35.dist-info/top_level.txt
mypyautogen20240904-0.2.35.dist-info/RECORD
